nka/__init__.py
nka/_input_pipeline.py
nka/_mmr.py
nka/_proposals.py
nka/model.py
nka/backend/__init__.py
nka/backend/_abc_embedder.py
nka/backend/_sentencetransformers.py
nka/backend/_utils.py
nka-1.0.2.dist-info/AUTHORS.rst
nka-1.0.2.dist-info/LICENSE
nka-1.0.2.dist-info/METADATA
nka-1.0.2.dist-info/WHEEL
nka-1.0.2.dist-info/top_level.txt
nka-1.0.2.dist-info/RECORD
