Metadata-Version: 2.1
Name: nka
Version: 1.0.2
Summary: An example package. Generated with cookiecutter-pylibrary.
Home-page: https://github.com/tobibias/neural-keyword-assignment
Author: Tobias Höfer
Author-email: tobias.hoefer.hm@gmail.com
License: MIT
Project-URL: Documentation, https://neural-keyword-assignment.readthedocs.io/
Project-URL: Changelog, https://neural-keyword-assignment.readthedocs.io/en/latest/changelog.html
Project-URL: Issue Tracker, https://github.com/tobibias/neural-keyword-assignment/issues
Platform: UNKNOWN
Classifier: Development Status :: 5 - Production/Stable
Classifier: Intended Audience :: Developers
Classifier: License :: OSI Approved :: MIT License
Classifier: Operating System :: Unix
Classifier: Operating System :: POSIX
Classifier: Operating System :: Microsoft :: Windows
Classifier: Programming Language :: Python
Classifier: Programming Language :: Python :: 3
Classifier: Programming Language :: Python :: 3 :: Only
Classifier: Programming Language :: Python :: 3.6
Classifier: Programming Language :: Python :: 3.7
Classifier: Programming Language :: Python :: 3.8
Classifier: Programming Language :: Python :: 3.9
Classifier: Programming Language :: Python :: 3.10
Classifier: Programming Language :: Python :: Implementation :: CPython
Classifier: Programming Language :: Python :: Implementation :: PyPy
Classifier: Topic :: Utilities
Requires-Python: >=3.6
License-File: LICENSE
License-File: AUTHORS.rst
Requires-Dist: torch (==1.9.0)
Requires-Dist: sentence-transformers (>=0.3.8)
Requires-Dist: spacy (>=3.0.1)
Requires-Dist: spacy-transformers
Requires-Dist: numpy (>=1.18.5)
